README.rst
setup.py
bin/dbgcode
dbgcode/__init__.py
dbgcode/api.py
dbgcode/core.py
dbgcode.egg-info/PKG-INFO
dbgcode.egg-info/SOURCES.txt
dbgcode.egg-info/dependency_links.txt
dbgcode.egg-info/top_level.txt
tests/__init__.py