Metadata-Version: 1.0
Name: dbgcode
Version: 0.1
Summary: write debug code with confidence
Home-page: UNKNOWN
Author: Ali Faki
Author-email: alifaki077@gmail.com
License: MIT
Platform: UNKNOWN
